Metadata-Version: 2.0
Name: odoo9-addon-website-seo-redirection
Version: 9.0.1.1.1
Summary: Redirect any controller to the URL of your dreams
Home-page: https://tecnativa.com/
Author: Tecnativa, LasLabs, Odoo Community Association (OCA)
Author-email: support@odoo-community.org
License: LGPL-3
Platform: UNKNOWN
Classifier: Programming Language :: Python :: 2.7
Classifier: Framework :: Odoo
Classifier: License :: OSI Approved :: GNU Lesser General Public License v3 (LGPLv3)
Requires-Dist: odoo (<9.1a,>=9.0a)
